Workbook
Name Slicer_Region: #N/A
Name Slicer_Segment: #N/A
Name Slicer_Year: #N/A

Sheet Detail1
A1: Details for Sum of Profit - Category: Technology
A3: Row ID | B3: Order ID | C3: Year | D3: Order Date | E3: Ship Date | F3: Ship Mode | G3: Customer ID | H3: Customer Name | I3: Segment | J3: Country | K3: City | L3: State | M3: Postal Code | N3: Region | O3: Product ID | P3: Category | Q3: Sub-Category | R3: Product Name | S3: Sales | T3: Quantity | U3: Discount | V3: Profit
A4: 9992 | B4: CA-2014-121258 | C4: 2014 | D4: 41697 | E4: 41702 | F4: Standard Class | G4: DB-13060 | H4: Dave Brooks | I4: Consumer | J4: United States | K4: Costa Mesa | L4: California | M4: 92627 | N4: West | O4: TEC-PH-10003645 | P4: Technology | Q4: Phones | R4: Aastra 57i VoIP phone | S4: 258.576 | T4: 2 | U4: 0.2 | V4: 19.3932
A5: 9989 | B5: CA-2014-163629 | C5: 2014 | D5: 41961 | E5: 41965 | F5: Standard Class | G5: RA-19885 | H5: Ruben Ausman | I5: Corporate | J5: United States | K5: Athens | L5: Georgia | M5: 30605 | N5: South | O5: TEC-PH-10004006 | P5: Technology | Q5: Phones | R5: Panasonic KX - TS880B Telephone | S5: 206.1 | T5: 5 | U5: 0 | V5: 55.647
A6: 9988 | B6: CA-2014-163629 | C6: 2014 | D6: 41961 | E6: 41965 | F6: Standard Class | G6: RA-19885 | H6: Ruben Ausman | I6: Corporate | J6: United States | K6: Athens | L6: Georgia | M6: 30605 | N6: South | O6: TEC-AC-10001539 | P6: Technology | Q6: Accessories | R6: Logitech G430 Surround Sound Gaming Headset with Dolby 7.1 Technology | S6: 79.99 | T6: 1 | U6: 0 | V6: 28.7964
A7: 9987 | B7: CA-2013-125794 | C7: 2013 | D7: 41547 | E7: 41551 | F7: Standard Class | G7: ML-17410 | H7: Maris LaWare | I7: Consumer | J7: United States | K7: Los Angeles | L7: California | M7: 90008 | N7: West | O7: TEC-AC-10003399 | P7: Technology | Q7: Accessories | R7: Memorex Mini Travel Drive 64 GB USB 2.0 Flash Drive | S7: 36.24 | T7: 1 | U7: 0 | V7: 15.2208
A8: 9984 | B8: US-2013-157728 | C8: 2013 | D8: 41540 | E8: 41546 | F8: Standard Class | G8: RC-19960 | H8: Ryan Crowe | I8: Consumer | J8: United States | K8: Grand Rapids | L8: Michigan | M8: 49505 | N8: Central | O8: TEC-PH-10001305 | P8: Technology | Q8: Phones | R8: Panasonic KX TS208W Corded phone | S8: 97.98 | T8: 2 | U8: 0 | V8: 27.4344
A9: 9977 | B9: US-2013-103674 | C9: 2013 | D9: 41615 | E9: 41619 | F9: Standard Class | G9: AP-10720 | H9: Anne Pryor | I9: Home Office | J9: United States | K9: Los Angeles | L9: California | M9: 90032 | N9: West | O9: TEC-PH-10002496 | P9: Technology | Q9: Phones | R9: Cisco SPA301 | S9: 249.584 | T9: 2 | U9: 0.2 | V9: 31.198
A10: 9974 | B10: US-2013-103674 | C10: 2013 | D10: 41615 | E10: 41619 | F10: Standard Class | G10: AP-10720 | H10: Anne Pryor | I10: Home Office | J10: United States | K10: Los Angeles | L10: California | M10: 90032 | N10: West | O10: TEC-PH-10004080 | P10: Technology | Q10: Phones | R10: Avaya 5410 Digital phone | S10: 271.96 | T10: 5 | U10: 0.2 | V10: 27.196
A11: 8 | B11: CA-2011-115812 | C11: 2011 | D11: 40703 | E11: 40708 | F11: Standard Class | G11: BH-11710 | H11: Brosina Hoffman | I11: Consumer | J11: United States | K11: Los Angeles | L11: California | M11: 90032 | N11: West | O11: TEC-PH-10002275 | P11: Technology | Q11: Phones | R11: Mitel 5320 IP Phone VoIP phone | S11: 907.152 | T11: 6 | U11: 0.2 | V11: 90.7152
A12: 9961 | B12: CA-2014-141446 | C12: 2014 | D12: 41899 | E12: 41901 | F12: Second Class | G12: CL-12700 | H12: Craig Leslie | I12: Home Office | J12: United States | K12: Florence | L12: Kentucky | M12: 41042 | N12: South | O12: TEC-AC-10002305 | P12: Technology | Q12: Accessories | R12: KeyTronic E03601U1 - Keyboard - Beige | S12: 18 | T12: 1 | U12: 0 | V12: 3.24
A13: 9951 | B13: CA-2014-121559 | C13: 2014 | D13: 41792 | E13: 41794 | F13: Second Class | G13: HW-14935 | H13: Helen Wasserman | I13: Corporate | J13: United States | K13: Indianapolis | L13: Indiana | M13: 46203 | N13: Central | O13: TEC-AC-10001714 | P13: Technology | Q13: Accessories | R13: Logitech MX Performance Wireless Mouse | S13: 39.89 | T13: 1 | U13: 0 | V13: 14.7593
A14: 9950 | B14: CA-2014-121559 | C14: 2014 | D14: 41792 | E14: 41794 | F14: Second Class | G14: HW-14935 | H14: Helen Wasserman | I14: Corporate | J14: United States | K14: Indianapolis | L14: Indiana | M14: 46203 | N14: Central | O14: TEC-AC-10004568 | P14: Technology | Q14: Accessories | R14: Maxell LTO Ultrium - 800 GB | S14: 83.97 | T14: 3 | U14: 0 | V14: 15.9543
A15: 12 | B15: CA-2011-115812 | C15: 2011 | D15: 40703 | E15: 40708 | F15: Standard Class | G15: BH-11710 | H15: Brosina Hoffman | I15: Consumer | J15: United States | K15: Los Angeles | L15: California | M15: 90032 | N15: West | O15: TEC-PH-10002033 | P15: Technology | Q15: Phones | R15: Konftel 250 Conference phone - Charcoal black | S15: 911.424 | T15: 4 | U15: 0.2 | V15: 68.3568
... A175: 9153 | B175: US-2012-106873 | C175: 2012 | D175: 41176 | E175: 41181 | F175: Second Class | G175: KM-16720 | H175: Kunst Miller | I175: Consumer | J175: United States | K175: Avondale | L175: Arizona | M175: 85323 | N175: West | O175: TEC-AC-10002345 | P175: Technology | Q175: Accessories | R175: HP Standard 104 key PS/2 Keyboard | S175: 23.2 | T175: 2 | U175: 0.2 | V175: 1.45
A176: 9147 | B176: US-2013-165505 | C176: 2013 | D176: 41297 | E176: 41301 | F176: Standard Class | G176: CB-12535 | H176: Claudia Bergmann | I176: Corporate | J176: United States | K176: Burlington | L176: Vermont | M176: 05408 | N176: East | O176: TEC-AC-10002926 | P176: Technology | Q176: Accessories | R176: Logitech Wireless Marathon Mouse M705 | S176: 99.98 | T176: 2 | U176: 0 | V176: 42.9914
A177: 9144 | B177: US-2014-166688 | C177: 2014 | D177: 41780 | E177: 41786 | F177: Standard Class | G177: RD-19480 | H177: Rick Duston | I177: Consumer | J177: United States | K177: Las Vegas | L177: Nevada | M177: 89115 | N177: West | O177: TEC-PH-10004094 | P177: Technology | Q177: Phones | R177: Motorola L703CM | S177: 1123.128 | T177: 9 | U177: 0.2 | V177: 70.1955
A178: 9142 | B178: CA-2013-139409 | C178: 2013 | D178: 41523 | E178: 41525 | F178: First Class | G178: FW-14395 | H178: Fred Wasserman | I178: Corporate | J178: United States | K178: New York City | L178: New York | M178: 10011 | N178: East | O178: TEC-PH-10003988 | P178: Technology | Q178: Phones | R178: LF Elite 3D Dazzle Designer Hard Case Cover, Lf Stylus Pen and Wiper For Apple Iphone 5c Mini Lite | S178: 43.6 | T178: 4 | U178: 0 | V178: 12.208
A179: 9141 | B179: CA-2014-123029 | C179: 2014 | D179: 41913 | E179: 41915 | F179: Second Class | G179: BT-11530 | H179: Bradley Talbott | I179: Home Office | J179: United States | K179: Los Angeles | L179: California | M179: 90049 | N179: West | O179: TEC-AC-10002402 | P179: Technology | Q179: Accessories | R179: Razer Kraken PRO Over Ear PC and Music Headset | S179: 159.98 | T179: 2 | U179: 0 | V179: 47.994
A180: 9140 | B180: CA-2011-106971 | C180: 2011 | D180: 40788 | E180: 40794 | F180: Standard Class | G180: BM-11785 | H180: Bryan Mills | I180: Consumer | J180: United States | K180: Buffalo Grove | L180: Illinois | M180: 60089 | N180: Central | O180: TEC-AC-10000844 | P180: Technology | Q180: Accessories | R180: Logitech Gaming G510s - Keyboard | S180: 475.944 | T180: 7 | U180: 0.2 | V180: 95.1888
A181: 9139 | B181: CA-2011-123400 | C181: 2011 | D181: 40577 | E181: 40584 | F181: Standard Class | G181: EB-13930 | H181: Eric Barreto | I181: Consumer | J181: United States | K181: Saint Petersburg | L181: Florida | M181: 33710 | N181: South | O181: TEC-PH-10002890 | P181: Technology | Q181: Phones | R181: AT&T 17929 Lendline Telephone | S181: 180.96 | T181: 5 | U181: 0.2 | V181: 13.572
A182: 9134 | B182: CA-2012-157805 | C182: 2012 | D182: 41152 | E182: 41156 | F182: Standard Class | G182: RH-19510 | H182: Rick Huthwaite | I182: Home Office | J182: United States | K182: San Diego | L182: California | M182: 92037 | N182: West | O182: TEC-PH-10004447 | P182: Technology | Q182: Phones | R182: Toshiba IPT2010-SD IP Telephone | S182: 555.96 | T182: 5 | U182: 0.2 | V182: 41.697
A183: 9116 | B183: CA-2014-153045 | C183: 2014 | D183: 41659 | E183: 41664 | F183: Second Class | G183: NS-18505 | H183: Neola Schneider | I183: Consumer | J183: United States | K183: Philadelphia | L183: Pennsylvania | M183: 19140 | N183: East | O183: TEC-PH-10001817 | P183: Technology | Q183: Phones | R183: Wilson Electronics DB Pro Signal Booster | S183: 429.6 | T183: 2 | U183: 0.4 | V183: -93.08
A184: 9115 | B184: CA-2013-135461 | C184: 2013 | D184: 41312 | E184: 41315 | F184: Second Class | G184: EB-13975 | H184: Erica Bern | I184: Corporate | J184: United States | K184: Los Angeles | L184: California | M184: 90049 | N184: West | O184: TEC-PH-10004094 | P184: Technology | Q184: Phones | R184: Motorola L703CM | S184: 623.96 | T184: 5 | U184: 0.2 | V184: 38.9975
A185: 182 | B185: CA-2011-166191 | C185: 2011 | D185: 40882 | E185: 40886 | F185: Second Class | G185: DK-13150 | H185: David Kendrick | I185: Corporate | J185: United States | K185: Decatur | L185: Illinois | M185: 62521 | N185: Central | O185: TEC-AC-10004659 | P185: Technology | Q185: Accessories | R185: Imation Secure+ Hardware Encrypted USB 2.0 Flash Drive; 16GB | S185: 408.744 | T185: 7 | U185: 0.2 | V185: 76.6395
A186: 183 | B186: CA-2011-158274 | C186: 2011 | D186: 40866 | E186: 40871 | F186: Second Class | G186: RM-19675 | H186: Robert Marley | I186: Home Office | J186: United States | K186: Monroe | L186: Louisiana | M186: 71203 | N186: South | O186: TEC-PH-10003273 | P186: Technology | Q186: Phones | R186: AT&T TR1909W | S186: 503.96 | T186: 4 | U186: 0 | V186: 131.0296
A187: 184 | B187: CA-2011-158274 | C187: 2011 | D187: 40866 | E187: 40871 | F187: Second Class | G187: RM-19675 | H187: Robert Marley | I187: Home Office | J187: United States | K187: Monroe | L187: Louisiana | M187: 71203 | N187: South | O187: TEC-PH-10004896 | P187: Technology | Q187: Phones | R187: Nokia Lumia 521 (T-Mobile) | S187: 149.95 | T187: 5 | U187: 0 | V187: 41.986
A188: 185 | B188: CA-2011-158274 | C188: 2011 | D188: 40866 | E188: 40871 | F188: Second Class | G188: RM-19675 | H188: Robert Marley | I188: Home Office | J188: United States | K188: Monroe | L188: Louisiana | M188: 71203 | N188: South | O188: TEC-AC-10002345 | P188: Technology | Q188: Accessories | R188: HP Standard 104 key PS/2 Keyboard | S188: 29 | T188: 2 | U188: 0 | V188: 7.25
... A283: 8800 | B283: CA-2011-116666 | C283: 2011 | D283: 40671 | E283: 40673 | F283: First Class | G283: KT-16480 | H283: Kean Thornton | I283: Consumer | J283: United States | K283: Philadelphia | L283: Pennsylvania | M283: 19134 | N283: East | O283: TEC-CO-10001449 | P283: Technology | Q283: Copiers | R283: Hewlett Packard LaserJet 3310 Copier | S283: 1799.97 | T283: 5 | U283: 0.4 | V283: 239.996
A284: 8799 | B284: US-2013-150140 | C284: 2013 | D284: 41371 | E284: 41375 | F284: Standard Class | G284: VM-21685 | H284: Valerie Mitchum | I284: Home Office | J284: United States | K284: Burlington | L284: Vermont | M284: 05408 | N284: East | O284: TEC-PH-10002555 | P284: Technology | Q284: Phones | R284: Nortel Meridian M5316 Digital phone | S284: 1294.75 | T284: 5 | U284: 0 | V284: 336.635
A285: 282 | B285: US-2012-161991 | C285: 2012 | D285: 41178 | E285: 41180 | F285: Second Class | G285: SC-20725 | H285: Steven Cartwright | I285: Consumer | J285: United States | K285: Houston | L285: Texas | M285: 77070 | N285: Central | O285: TEC-PH-10001760 | P285: Technology | Q285: Phones | R285: Bose SoundLink Bluetooth Speaker | S285: 1114.4 | T285: 7 | U285: 0.2 | V285: 376.11
A286: 8796 | B286: CA-2011-162992 | C286: 2011 | D286: 40896 | E286: 40898 | F286: First Class | G286: BP-11095 | H286: Bart Pistole | I286: Corporate | J286: United States | K286: Los Angeles | L286: California | M286: 90008 | N286: West | O286: TEC-PH-10002085 | P286: Technology | Q286: Phones | R286: Clarity 53712 | S286: 211.168 | T286: 4 | U286: 0.2 | V286: 15.8376
A287: 8795 | B287: CA-2011-162992 | C287: 2011 | D287: 40896 | E287: 40898 | F287: First Class | G287: BP-11095 | H287: Bart Pistole | I287: Corporate | J287: United States | K287: Los Angeles | L287: California | M287: 90008 | N287: West | O287: TEC-PH-10001944 | P287: Technology | Q287: Phones | R287: Wi-Ex zBoost YX540 Cellular Phone Signal Booster | S287: 583.8 | T287: 5 | U287: 0.2 | V287: 72.975
A288: 285 | B288: CA-2012-130883 | C288: 2012 | D288: 41178 | E288: 41184 | F288: Standard Class | G288: TB-21520 | H288: Tracy Blumstein | I288: Consumer | J288: United States | K288: Portland | L288: Oregon | M288: 97206 | N288: West | O288: TEC-AC-10001956 | P288: Technology | Q288: Accessories | R288: Microsoft Arc Touch Mouse | S288: 239.8 | T288: 5 | U288: 0.2 | V288: 47.96
A289: 8792 | B289: CA-2014-162075 | C289: 2014 | D289: 41717 | E289: 41723 | F289: Standard Class | G289: TT-21220 | H289: Thomas Thornton | I289: Consumer | J289: United States | K289: Houston | L289: Texas | M289: 77041 | N289: Central | O289: TEC-PH-10001557 | P289: Technology | Q289: Phones | R289: Pyle PMP37LED | S289: 537.544 | T289: 7 | U289: 0.2 | V289: 47.0351
A290: 8788 | B290: CA-2014-145765 | C290: 2014 | D290: 41788 | E290: 41793 | F290: Standard Class | G290: CM-11815 | H290: Candace McMahon | I290: Corporate | J290: United States | K290: Phoenix | L290: Arizona | M290: 85023 | N290: West | O290: TEC-AC-10000844 | P290: Technology | Q290: Accessories | R290: Logitech Gaming G510s - Keyboard | S290: 271.968 | T290: 4 | U290: 0.2 | V290: 54.3936
A291: 8786 | B291: CA-2014-145765 | C291: 2014 | D291: 41788 | E291: 41793 | F291: Standard Class | G291: CM-11815 | H291: Candace McMahon | I291: Corporate | J291: United States | K291: Phoenix | L291: Arizona | M291: 85023 | N291: West | O291: TEC-PH-10001305 | P291: Technology | Q291: Phones | R291: Panasonic KX TS208W Corded phone | S291: 195.96 | T291: 5 | U291: 0.2 | V291: 19.596
A292: 8770 | B292: CA-2013-151148 | C292: 2013 | D292: 41530 | E292: 41531 | F292: Same Day | G292: PO-19180 | H292: Philisse Overcash | I292: Home Office | J292: United States | K292: Louisville | L292: Colorado | M292: 80027 | N292: West | O292: TEC-PH-10001870 | P292: Technology | Q292: Phones | R292: Lunatik TT5L-002 Taktik Strike Impact Protection System for iPhone 5 | S292: 146.952 | T292: 3 | U292: 0.2 | V292: 9.1845
A293: 8769 | B293: CA-2012-151722 | C293: 2012 | D293: 41187 | E293: 41191 | F293: Standard Class | G293: IL-15100 | H293: Ivan Liston | I293: Consumer | J293: United States | K293: Columbus | L293: Ohio | M293: 43229 | N293: East | O293: TEC-AC-10000892 | P293: Technology | Q293: Accessories | R293: NETGEAR N750 Dual Band Wi-Fi Gigabit Router | S293: 288 | T293: 4 | U293: 0.2 | V293: 57.6
A294: 8753 | B294: CA-2013-105662 | C294: 2013 | D294: 41400 | E294: 41404 | F294: Standard Class | G294: RB-19465 | H294: Rick Bensley | I294: Home Office | J294: United States | K294: Tallahassee | L294: Florida | M294: 32303 | N294: South | O294: TEC-PH-10001198 | P294: Technology | Q294: Phones | R294: Avaya 4621SW VoIP phone | S294: 177.48 | T294: 3 | U294: 0.2 | V294: 19.9665
A295: 292 | B295: CA-2013-110772 | C295: 2013 | D295: 41599 | E295: 41603 | F295: Second Class | G295: NZ-18565 | H295: Nick Zandusky | I295: Home Office | J295: United States | K295: Columbus | L295: Ohio | M295: 43229 | N295: East | O295: TEC-AC-10002001 | P295: Technology | Q295: Accessories | R295: Logitech Wireless Gaming Headset G930 | S295: 255.984 | T295: 2 | U295: 0.2 | V295: 54.3966
A296: 8751 | B296: US-2012-163825 | C296: 2012 | D296: 41076 | E296: 41079 | F296: First Class | G296: LC-16885 | H296: Lena Creighton | I296: Consumer | J296: United States | K296: New York City | L296: New York | M296: 10009 | N296: East | O296: TEC-PH-10004922 | P296: Technology | Q296: Phones | R296: RCA Visys Integrated PBX 8-Line Router | S296: 133.98 | T296: 2 | U296: 0 | V296: 33.495
... A1764: 2242 | B1764: US-2013-126893 | C1764: 2013 | D1764: 41605 | E1764: 41610 | F1764: Standard Class | G1764: CT-11995 | H1764: Carol Triggs | I1764: Consumer | J1764: United States | K1764: Philadelphia | L1764: Pennsylvania | M1764: 19134 | N1764: East | O1764: TEC-PH-10004165 | P1764: Technology | Q1764: Phones | R1764: Mitel MiVoice 5330e IP Phone | S1764: 494.982 | T1764: 3 | U1764: 0.4 | V1764: -115.4958
A1765: 2235 | B1765: CA-2014-104066 | C1765: 2014 | D1765: 41979 | E1765: 41984 | F1765: Standard Class | G1765: QJ-19255 | H1765: Quincy Jones | I1765: Corporate | J1765: United States | K1765: Burlington | L1765: Vermont | M1765: 05408 | N1765: East | O1765: TEC-AC-10001013 | P1765: Technology | Q1765: Accessories | R1765: Logitech ClearChat Comfort/USB Headset H390 | S1765: 205.03 | T1765: 7 | U1765: 0 | V1765: 67.6599
A1766: 2234 | B1766: CA-2012-123232 | C1766: 2012 | D1766: 41257 | E1766: 41259 | F1766: Second Class | G1766: DJ-13630 | H1766: Doug Jacobs | I1766: Consumer | J1766: United States | K1766: Portland | L1766: Oregon | M1766: 97206 | N1766: West | O1766: TEC-PH-10001051 | P1766: Technology | Q1766: Phones | R1766: HTC One | S1766: 319.968 | T1766: 4 | U1766: 0.2 | V1766: 35.9964
A1767: 2228 | B1767: CA-2014-130771 | C1767: 2014 | D1767: 41850 | E1767: 41855 | F1767: Standard Class | G1767: LA-16780 | H1767: Laura Armstrong | I1767: Corporate | J1767: United States | K1767: Austin | L1767: Texas | M1767: 78745 | N1767: Central | O1767: TEC-PH-10002496 | P1767: Technology | Q1767: Phones | R1767: Cisco SPA301 | S1767: 124.792 | T1767: 1 | U1767: 0.2 | V1767: 15.599
A1768: 2222 | B1768: CA-2012-131884 | C1768: 2012 | D1768: 41249 | E1768: 41249 | F1768: Same Day | G1768: DK-13375 | H1768: Dennis Kane | I1768: Consumer | J1768: United States | K1768: Marion | L1768: Ohio | M1768: 43302 | N1768: East | O1768: TEC-PH-10001578 | P1768: Technology | Q1768: Phones | R1768: Polycom SoundStation2 EX Conference phone | S1768: 485.94 | T1768: 2 | U1768: 0.4 | V1768: -89.089
A1769: 2221 | B1769: CA-2014-130841 | C1769: 2014 | D1769: 41849 | E1769: 41853 | F1769: Standard Class | G1769: MH-17620 | H1769: Matt Hagelstein | I1769: Corporate | J1769: United States | K1769: San Francisco | L1769: California | M1769: 94110 | N1769: West | O1769: TEC-PH-10001817 | P1769: Technology | Q1769: Phones | R1769: Wilson Electronics DB Pro Signal Booster | S1769: 1145.6 | T1769: 4 | U1769: 0.2 | V1769: 100.24
A1770: 2210 | B1770: CA-2011-125556 | C1770: 2011 | D1770: 40861 | E1770: 40863 | F1770: Second Class | G1770: ML-17410 | H1770: Maris LaWare | I1770: Consumer | J1770: United States | K1770: Fairfield | L1770: Connecticut | M1770: 6824 | N1770: East | O1770: TEC-PH-10001079 | P1770: Technology | Q1770: Phones | R1770: Polycom SoundPoint Pro SE-225 Corded phone | S1770: 832.93 | T1770: 7 | U1770: 0 | V1770: 233.2204
A1771: 2208 | B1771: US-2011-103905 | C1771: 2011 | D1771: 40738 | E1771: 40744 | F1771: Standard Class | G1771: AW-10930 | H1771: Arthur Wiediger | I1771: Home Office | J1771: United States | K1771: Aurora | L1771: Illinois | M1771: 60505 | N1771: Central | O1771: TEC-PH-10001552 | P1771: Technology | Q1771: Phones | R1771: I Need's 3d Hello Kitty Hybrid Silicone Case Cover for HTC One X 4g with 3d Hello Kitty Stylus Pen Green/pink | S1771: 38.272 | T1771: 4 | U1771: 0.2 | V1771: 3.8272
A1772: 2202 | B1772: US-2011-165659 | C1772: 2011 | D1772: 40695 | E1772: 40700 | F1772: Standard Class | G1772: LT-17110 | H1772: Liz Thompson | I1772: Consumer | J1772: United States | K1772: Little Rock | L1772: Arkansas | M1772: 72209 | N1772: South | O1772: TEC-PH-10002563 | P1772: Technology | Q1772: Phones | R1772: Adtran 1202752G1 | S1772: 881.93 | T1772: 7 | U1772: 0 | V1772: 229.3018
A1773: 2196 | B1773: CA-2013-128412 | C1773: 2013 | D1773: 41619 | E1773: 41626 | F1773: Standard Class | G1773: AP-10915 | H1773: Arthur Prichep | I1773: Consumer | J1773: United States | K1773: Seattle | L1773: Washington | M1773: 98105 | N1773: West | O1773: TEC-AC-10003038 | P1773: Technology | Q1773: Accessories | R1773: Kingston Digital DataTraveler 16GB USB 2.0 | S1773: 44.75 | T1773: 5 | U1773: 0 | V1773: 8.5025
A1774: 2190 | B1774: CA-2014-143063 | C1774: 2014 | D1774: 41862 | E1774: 41867 | F1774: Standard Class | G1774: IL-15100 | H1774: Ivan Liston | I1774: Consumer | J1774: United States | K1774: Columbus | L1774: Indiana | M1774: 47201 | N1774: Central | O1774: TEC-PH-10003645 | P1774: Technology | Q1774: Phones | R1774: Aastra 57i VoIP phone | S1774: 1454.49 | T1774: 9 | U1774: 0 | V1774: 378.1674
A1775: 2187 | B1775: CA-2013-101378 | C1775: 2013 | D1775: 41470 | E1775: 41470 | F1775: Same Day | G1775: RH-19600 | H1775: Rob Haberlin | I1775: Consumer | J1775: United States | K1775: Huntsville | L1775: Alabama | M1775: 35810 | N1775: South | O1775: TEC-AC-10002345 | P1775: Technology | Q1775: Accessories | R1775: HP Standard 104 key PS/2 Keyboard | S1775: 29 | T1775: 2 | U1775: 0 | V1775: 7.25
A1776: 1773 | B1776: CA-2013-129686 | C1776: 2013 | D1776: 41606 | E1776: 41608 | F1776: Second Class | G1776: GG-14650 | H1776: Greg Guthrie | I1776: Corporate | J1776: United States | K1776: Chicago | L1776: Illinois | M1776: 60623 | N1776: Central | O1776: TEC-AC-10001266 | P1776: Technology | Q1776: Accessories | R1776: Memorex Micro Travel Drive 8 GB | S1776: 62.4 | T1776: 6 | U1776: 0.2 | V1776: 19.5
A1777: 2184 | B1777: CA-2013-128818 | C1777: 2013 | D1777: 41402 | E1777: 41406 | F1777: Standard Class | G1777: CJ-12010 | H1777: Caroline Jumper | I1777: Consumer | J1777: United States | K1777: New York City | L1777: New York | M1777: 10009 | N1777: East | O1777: TEC-AC-10001767 | P1777: Technology | Q1777: Accessories | R1777: SanDisk Ultra 64 GB MicroSDHC Class 10 Memory Card | S1777: 199.95 | T1777: 5 | U1777: 0 | V1777: 21.9945
... A1850: 1851 | B1850: CA-2012-160472 | C1850: 2012 | D1850: 41110 | E1850: 41115 | F1850: Second Class | G1850: RK-19300 | H1850: Ralph Kennedy | I1850: Consumer | J1850: United States | K1850: South Bend | L1850: Indiana | M1850: 46614 | N1850: Central | O1850: TEC-AC-10002253 | P1850: Technology | Q1850: Accessories | R1850: Imation Bio 8GB USB Flash Drive Imation Corp | S1850: 831.2 | T1850: 5 | U1850: 0 | V1850: 124.68

Sheet my all pivot tables
A3: Row Labels | B3: Sum of Sales | C3: Sum of Profit | F3: Row Labels | G3: Sum of Profit | I3: Category | J3: Profit
A4: Jan | B4: 5539.796 | C4: 320.6542 | F4: Technology | G4: 19300.917 | I4: =F4 -> Technology | J4: =G4 -> 19300.917
A5: Feb | B5: 4950.902 | C5: 486.2289 | F5: Office Supplies | G5: 11714.305 | I5: =F5 -> Office Supplies | J5: =G5 -> 11714.305 | L5: Row Labels | M5: Sum of Sales | P5: Row Labels | Q5: Sum of Sales | S5: State | T5: Sales
A6: Mar | B6: 6850.226 | C6: 954.0345 | F6: Furniture | G6: 2180.1244 | I6: =F6 -> Furniture | J6: =G6 -> 2180.1244 | L6: Furniture | M6: 0.28537811 | P6: Connecticut | Q6: 5307.21 | S6: =P6 -> Connecticut | T6: =Q6 -> 5307.21 | V6: Row Labels | W6: Sum of Sales
A7: Apr | B7: 10327.692 | C7: 1574.4102 | F7: Grand Total | G7: 33195.346 | I7: =F7 -> Grand Total | J7: =G7 -> 33195.346 | L7: Office Supplies | M7: 0.3059806 | P7: Delaware | Q7: 13754.983 | S7: =P7 -> Delaware | T7: =Q7 -> 13754.983 | V7: Accessories | W7: 14836.79
A8: May | B8: 6889.933 | C8: 711.3313 | L8: Technology | M8: 0.40864129 | P8: District of Columbia | Q8: 77.76 | S8: =P8 -> District of Columbia | T8: =Q8 -> 77.76 | V8: Storage | W8: 20156.57
A9: Jun | B9: 12760.375 | C9: 3038.634 | L9: Grand Total | M9: 1 | P9: Maryland | Q9: 9451.6 | S9: =P9 -> Maryland | T9: =Q9 -> 9451.6 | V9: Copiers | W9: 24399.87
A10: Jul | B10: 13509.781 | C10: 818.6384 | P10: Massachusetts | Q10: 8143.076 | S10: =P10 -> Massachusetts | T10: =Q10 -> 8143.076 | V10: Chairs | W10: 31232.66
A11: Aug | B11: 21971.358 | C11: 2545.5305 | P11: New Hampshire | Q11: 1509.43 | S11: =P11 -> New Hampshire | T11: =Q11 -> 1509.43 | V11: Phones | W11: 36074.57
A12: Sep | B12: 32230.554 | C12: 2404.881 | P12: New Jersey | Q12: 9483.55 | S12: =P12 -> New Jersey | T12: =Q12 -> 9483.55 | V12: Grand Total | W12: 126700.46
A13: Oct | B13: 32490.744 | C13: 7725.647 | P13: New York | Q13: 93922.995 | S13: =P13 -> New York | T13: =Q13 -> 93922.995
A14: Nov | B14: 41523.965 | C14: 8821.0827 | P14: Ohio | Q14: 23421.362 | S14: =P14 -> Ohio | T14: =Q14 -> 23421.362
A15: Dec | B15: 24194.09 | C15: 3794.2735 | P15: Pennsylvania | Q15: 42688.306 | S15: =P15 -> Pennsylvania | T15: =Q15 -> 42688.306
A16: Grand Total | B16: 213239.42 | C16: 33195.346 | P16: Rhode Island | Q16: 3427.11 | S16: =P16 -> Rhode Island | T16: =Q16 -> 3427.11
P17: Vermont | Q17: 842.21 | S17: =P17 -> Vermont | T17: =Q17 -> 842.21
P18: West Virginia | Q18: 1209.824 | S18: =P18 -> West Virginia | T18: =Q18 -> 1209.824
P19: Grand Total | Q19: 213239.42 | S19: =P19 -> Grand Total | T19: =Q19 -> 213239.42
S20: =P20 -> 0 | T20: =Q20 -> 0
S21: =P21 -> 0 | T21: =Q21 -> 0
S22: =P22 -> 0 | T22: =Q22 -> 0
S23: =P23 -> 0 | T23: =Q23 -> 0
S24: =P24 -> 0 | T24: =Q24 -> 0
S25: =P25 -> 0 | T25: =Q25 -> 0
S26: =P26 -> 0 | T26: =Q26 -> 0
S27: =P27 -> 0 | T27: =Q27 -> 0
S28: =P28 -> 0 | T28: =Q28 -> 0
S29: =P29 -> 0 | T29: =Q29 -> 0
S30: =P30 -> 0 | T30: =Q30 -> 0
S31: =P31 -> 0 | T31: =Q31 -> 0
... S55: =P55 -> 0 | T55: =Q55 -> 0

Sheet kpi
A3: Row Labels | B3: Sum of Sales | D3: Row Labels | E3: Sum of Profit | G3: Row Labels | H3: Sum of Quantity | J3: Row Labels | K3: Count of Order ID | M3: Row Labels | N3: Sum of Profit Margine
A4: Jan | B4: 5539.796 | D4: Jan | E4: 320.6542 | G4: Jan | H4: 80 | J4: Jan | K4: 25 | M4: Jan | N4: 0.057881951
A5: Feb | B5: 4950.902 | D5: Feb | E5: 486.2289 | G5: Feb | H5: 97 | J5: Feb | K5: 28 | M5: Feb | N5: 0.098210165
A6: Mar | B6: 6850.226 | D6: Mar | E6: 954.0345 | G6: Mar | H6: 212 | J6: Mar | K6: 62 | M6: Mar | N6: 0.13927051
A7: Apr | B7: 10327.692 | D7: Apr | E7: 1574.4102 | G7: Apr | H7: 208 | J7: Apr | K7: 63 | M7: Apr | N7: 0.1524455
A8: May | B8: 6889.933 | D8: May | E8: 711.3313 | G8: May | H8: 193 | J8: May | K8: 57 | M8: May | N8: 0.10324212
A9: Jun | B9: 12760.375 | D9: Jun | E9: 3038.634 | G9: Jun | H9: 242 | J9: Jun | K9: 61 | M9: Jun | N9: 0.23813046
A10: Jul | B10: 13509.781 | D10: Jul | E10: 818.6384 | G10: Jul | H10: 302 | J10: Jul | K10: 79 | M10: Jul | N10: 0.060595979
A11: Aug | B11: 21971.358 | D11: Aug | E11: 2545.5305 | G11: Aug | H11: 225 | J11: Aug | K11: 52 | M11: Aug | N11: 0.11585677
A12: Sep | B12: 32230.554 | D12: Sep | E12: 2404.881 | G12: Sep | H12: 504 | J12: Sep | K12: 147 | M12: Sep | N12: 0.074614945
A13: Oct | B13: 32490.744 | D13: Oct | E13: 7725.647 | G13: Oct | H13: 329 | J13: Oct | K13: 86 | M13: Oct | N13: 0.23777994
A14: Nov | B14: 41523.965 | D14: Nov | E14: 8821.0827 | G14: Nov | H14: 505 | J14: Nov | K14: 121 | M14: Nov | N14: 0.21243354
A15: Dec | B15: 24194.09 | D15: Dec | E15: 3794.2735 | G15: Dec | H15: 518 | J15: Dec | K15: 141 | M15: Dec | N15: 0.15682646
A16: Grand Total | B16: 213239.42 | D16: Grand Total | E16: 33195.346 | G16: Grand Total | H16: 3415 | J16: Grand Total | K16: 922 | M16: Grand Total | N16: 0.15567172
B17: =B16 -> 213239.42 | E17: =E16 -> 33195.346 | H17: =H16 -> 3415 | K17: =K16 -> 922 | N17: =N16 -> 0.15567172

Sheet KPI YOY
A3: Row Labels | B3: Sum of Sales | C3: Sum of Profit | D3: Sum of Quantity | E3: Count of Order ID | F3: Sum of Profit Margine
A4: 2011 | B4: 128680.46 | C4: 17059.61 | D4: 1986 | E4: 517 | F4: 0.13257343
A5: 2012 | B5: 156332.06 | C5: 21091.013 | D5: 2382 | E5: 644 | F5: 0.13491163
A6: 2013 | B6: 180529.31 | C6: 20176.811 | D6: 2835 | E6: 765 | F6: 0.11176474
A7: 2014 | B7: 213239.42 | C7: 33195.346 | D7: 3415 | E7: 922 | F7: 0.15567172
I8: =(B7/B6)-1 -> 0.18119 | J8: =(C7/C6)-1 -> 0.64522261 | K8: =(D7/D6)-1 -> 0.20458554 | L8: =(E7/E6)-1 -> 0.20522876 | M8: =(F7/F6)-1 -> 0.39285179

Sheet Data
A1: Row ID | B1: Order ID | C1: Year | D1: Order Date | E1: Ship Date | F1: Ship Mode | G1: Customer ID | H1: Customer Name | I1: Segment | J1: Country | K1: City | L1: State | M1: Postal Code | N1: Region | O1: Product ID | P1: Category | Q1: Sub-Category | R1: Product Name | S1: Sales | T1: Quantity | U1: Discount | V1: Profit
A2: 1 | B2: CA-2013-152156 | C2: =YEAR(Data!$D2) -> 2013 | D2: 41587 | E2: 41590 | F2: Second Class | G2: CG-12520 | H2: Claire Gute | I2: Consumer | J2: United States | K2: Henderson | L2: Kentucky | M2: 42420 | N2: South | O2: FUR-BO-10001798 | P2: Furniture | Q2: Bookcases | R2: Bush Somerset Collection Bookcase | S2: 261.96 | T2: 2 | U2: 0 | V2: 41.9136
A3: 2 | B3: CA-2013-152156 | C3: =YEAR(Data!$D3) -> 2013 | D3: 41587 | E3: 41590 | F3: Second Class | G3: CG-12520 | H3: Claire Gute | I3: Consumer | J3: United States | K3: Henderson | L3: Kentucky | M3: 42420 | N3: South | O3: FUR-CH-10000454 | P3: Furniture | Q3: Chairs | R3: Hon Deluxe Fabric Upholstered Stacking Chairs, Rounded Back | S3: 731.94 | T3: 3 | U3: 0 | V3: 219.582
A4: 3 | B4: CA-2013-138688 | C4: =YEAR(Data!$D4) -> 2013 | D4: 41438 | E4: 41442 | F4: Second Class | G4: DV-13045 | H4: Darrin Van Huff | I4: Corporate | J4: United States | K4: Los Angeles | L4: California | M4: 90036 | N4: West | O4: OFF-LA-10000240 | P4: Office Supplies | Q4: Labels | R4: Self-Adhesive Address Labels for Typewriters by Universal | S4: 14.62 | T4: 2 | U4: 0 | V4: 6.8714
A5: 4 | B5: US-2012-108966 | C5: =YEAR(Data!$D5) -> 2012 | D5: 41193 | E5: 41200 | F5: Standard Class | G5: SO-20335 | H5: Sean O'Donnell | I5: Consumer | J5: United States | K5: Fort Lauderdale | L5: Florida | M5: 33311 | N5: South | O5: FUR-TA-10000577 | P5: Furniture | Q5: Tables | R5: Bretford CR4500 Series Slim Rectangular Table | S5: 957.5775 | T5: 5 | U5: 0.45 | V5: -383.031
A6: 5 | B6: US-2012-108966 | C6: =YEAR(Data!$D6) -> 2012 | D6: 41193 | E6: 41200 | F6: Standard Class | G6: SO-20335 | H6: Sean O'Donnell | I6: Consumer | J6: United States | K6: Fort Lauderdale | L6: Florida | M6: 33311 | N6: South | O6: OFF-ST-10000760 | P6: Office Supplies | Q6: Storage | R6: Eldon Fold 'N Roll Cart System | S6: 22.368 | T6: 2 | U6: 0.2 | V6: 2.5164
A7: 6 | B7: CA-2011-115812 | C7: =YEAR(Data!$D7) -> 2011 | D7: 40703 | E7: 40708 | F7: Standard Class | G7: BH-11710 | H7: Brosina Hoffman | I7: Consumer | J7: United States | K7: Los Angeles | L7: California | M7: 90032 | N7: West | O7: FUR-FU-10001487 | P7: Furniture | Q7: Furnishings | R7: Eldon Expressions Wood and Plastic Desk Accessories, Cherry Wood | S7: 48.86 | T7: 7 | U7: 0 | V7: 14.1694
A8: 7 | B8: CA-2011-115812 | C8: =YEAR(Data!$D8) -> 2011 | D8: 40703 | E8: 40708 | F8: Standard Class | G8: BH-11710 | H8: Brosina Hoffman | I8: Consumer | J8: United States | K8: Los Angeles | L8: California | M8: 90032 | N8: West | O8: OFF-AR-10002833 | P8: Office Supplies | Q8: Art | R8: Newell 322 | S8: 7.28 | T8: 4 | U8: 0 | V8: 1.9656
A9: 8 | B9: CA-2011-115812 | C9: =YEAR(Data!$D9) -> 2011 | D9: 40703 | E9: 40708 | F9: Standard Class | G9: BH-11710 | H9: Brosina Hoffman | I9: Consumer | J9: United States | K9: Los Angeles | L9: California | M9: 90032 | N9: West | O9: TEC-PH-10002275 | P9: Technology | Q9: Phones | R9: Mitel 5320 IP Phone VoIP phone | S9: 907.152 | T9: 6 | U9: 0.2 | V9: 90.7152
A10: 9 | B10: CA-2011-115812 | C10: =YEAR(Data!$D10) -> 2011 | D10: 40703 | E10: 40708 | F10: Standard Class | G10: BH-11710 | H10: Brosina Hoffman | I10: Consumer | J10: United States | K10: Los Angeles | L10: California | M10: 90032 | N10: West | O10: OFF-BI-10003910 | P10: Office Supplies | Q10: Binders | R10: DXL Angle-View Binders with Locking Rings by Samsill | S10: 18.504 | T10: 3 | U10: 0.2 | V10: 5.7825
A11: 10 | B11: CA-2011-115812 | C11: =YEAR(Data!$D11) -> 2011 | D11: 40703 | E11: 40708 | F11: Standard Class | G11: BH-11710 | H11: Brosina Hoffman | I11: Consumer | J11: United States | K11: Los Angeles | L11: California | M11: 90032 | N11: West | O11: OFF-AP-10002892 | P11: Office Supplies | Q11: Appliances | R11: Belkin F5C206VTEL 6 Outlet Surge | S11: 114.9 | T11: 5 | U11: 0 | V11: 34.47
A12: 11 | B12: CA-2011-115812 | C12: =YEAR(Data!$D12) -> 2011 | D12: 40703 | E12: 40708 | F12: Standard Class | G12: BH-11710 | H12: Brosina Hoffman | I12: Consumer | J12: United States | K12: Los Angeles | L12: California | M12: 90032 | N12: West | O12: FUR-TA-10001539 | P12: Furniture | Q12: Tables | R12: Chromcraft Rectangular Conference Tables | S12: 1706.184 | T12: 9 | U12: 0.2 | V12: 85.3092
A13: 12 | B13: CA-2011-115812 | C13: =YEAR(Data!$D13) -> 2011 | D13: 40703 | E13: 40708 | F13: Standard Class | G13: BH-11710 | H13: Brosina Hoffman | I13: Consumer | J13: United States | K13: Los Angeles | L13: California | M13: 90032 | N13: West | O13: TEC-PH-10002033 | P13: Technology | Q13: Phones | R13: Konftel 250 Conference phone - Charcoal black | S13: 911.424 | T13: 4 | U13: 0.2 | V13: 68.3568
... A2235: 2234 | B2235: CA-2012-123232 | C2235: =YEAR(Data!$D2235) -> 2012 | D2235: 41257 | E2235: 41259 | F2235: Second Class | G2235: DJ-13630 | H2235: Doug Jacobs | I2235: Consumer | J2235: United States | K2235: Portland | L2235: Oregon | M2235: 97206 | N2235: West | O2235: TEC-PH-10001051 | P2235: Technology | Q2235: Phones | R2235: HTC One | S2235: 319.968 | T2235: 4 | U2235: 0.2 | V2235: 35.9964
A2236: 2235 | B2236: CA-2014-104066 | C2236: =YEAR(Data!$D2236) -> 2014 | D2236: 41979 | E2236: 41984 | F2236: Standard Class | G2236: QJ-19255 | H2236: Quincy Jones | I2236: Corporate | J2236: United States | K2236: Burlington | L2236: Vermont | M2236: 05408 | N2236: East | O2236: TEC-AC-10001013 | P2236: Technology | Q2236: Accessories | R2236: Logitech ClearChat Comfort/USB Headset H390 | S2236: 205.03 | T2236: 7 | U2236: 0 | V2236: 67.6599
A2237: 2236 | B2237: CA-2012-145849 | C2237: =YEAR(Data!$D2237) -> 2012 | D2237: 41167 | E2237: 41169 | F2237: Second Class | G2237: CT-11995 | H2237: Carol Triggs | I2237: Consumer | J2237: United States | K2237: Indianapolis | L2237: Indiana | M2237: 46203 | N2237: Central | O2237: OFF-ST-10000025 | P2237: Office Supplies | Q2237: Storage | R2237: Fellowes Stor/Drawer Steel Plus Storage Drawers | S2237: 190.86 | T2237: 2 | U2237: 0 | V2237: 11.4516
A2238: 2237 | B2238: CA-2012-145849 | C2238: =YEAR(Data!$D2238) -> 2012 | D2238: 41167 | E2238: 41169 | F2238: Second Class | G2238: CT-11995 | H2238: Carol Triggs | I2238: Consumer | J2238: United States | K2238: Indianapolis | L2238: Indiana | M2238: 46203 | N2238: Central | O2238: OFF-AR-10000817 | P2238: Office Supplies | Q2238: Art | R2238: Manco Dry-Lighter Erasable Highlighter | S2238: 24.32 | T2238: 8 | U2238: 0 | V2238: 8.2688
A2239: 2238 | B2239: CA-2013-122322 | C2239: =YEAR(Data!$D2239) -> 2013 | D2239: 41471 | E2239: 41477 | F2239: Standard Class | G2239: RH-19510 | H2239: Rick Huthwaite | I2239: Home Office | J2239: United States | K2239: Provo | L2239: Utah | M2239: 84604 | N2239: West | O2239: OFF-SU-10000952 | P2239: Office Supplies | Q2239: Supplies | R2239: Fiskars Home & Office Scissors | S2239: 44.4 | T2239: 5 | U2239: 0 | V2239: 12.432
A2240: 2239 | B2240: CA-2014-166849 | C2240: =YEAR(Data!$D2240) -> 2014 | D2240: 41750 | E2240: 41756 | F2240: Standard Class | G2240: SJ-20125 | H2240: Sanjit Jacobs | I2240: Home Office | J2240: United States | K2240: Chicago | L2240: Illinois | M2240: 60610 | N2240: Central | O2240: FUR-FU-10004597 | P2240: Furniture | Q2240: Furnishings | R2240: Eldon Cleatmat Chair Mats for Medium Pile Carpets | S2240: 44.4 | T2240: 2 | U2240: 0.6 | V2240: -52.17
A2241: 2240 | B2241: CA-2013-146633 | C2241: =YEAR(Data!$D2241) -> 2013 | D2241: 41594 | E2241: 41596 | F2241: Second Class | G2241: TG-21310 | H2241: Toby Gnade | I2241: Consumer | J2241: United States | K2241: Los Angeles | L2241: California | M2241: 90049 | N2241: West | O2241: OFF-BI-10003527 | P2241: Office Supplies | Q2241: Binders | R2241: Fellowes PB500 Electric Punch Plastic Comb Binding Machine with Manual Bind | S2241: 1016.792 | T2241: 1 | U2241: 0.2 | V2241: 381.297
A2242: 2241 | B2242: CA-2013-146633 | C2242: =YEAR(Data!$D2242) -> 2013 | D2242: 41594 | E2242: 41596 | F2242: Second Class | G2242: TG-21310 | H2242: Toby Gnade | I2242: Consumer | J2242: United States | K2242: Los Angeles | L2242: California | M2242: 90049 | N2242: West | O2242: OFF-BI-10002982 | P2242: Office Supplies | Q2242: Binders | R2242: Avery Self-Adhesive Photo Pockets for Polaroid Photos | S2242: 38.136 | T2242: 7 | U2242: 0.2 | V2242: 13.3476
A2243: 2242 | B2243: US-2013-126893 | C2243: =YEAR(Data!$D2243) -> 2013 | D2243: 41605 | E2243: 41610 | F2243: Standard Class | G2243: CT-11995 | H2243: Carol Triggs | I2243: Consumer | J2243: United States | K2243: Philadelphia | L2243: Pennsylvania | M2243: 19134 | N2243: East | O2243: TEC-PH-10004165 | P2243: Technology | Q2243: Phones | R2243: Mitel MiVoice 5330e IP Phone | S2243: 494.982 | T2243: 3 | U2243: 0.4 | V2243: -115.4958
A2244: 2243 | B2244: CA-2014-103380 | C2244: =YEAR(Data!$D2244) -> 2014 | D2244: 41965 | E2244: 41969 | F2244: Standard Class | G2244: BF-11005 | H2244: Barry Franz | I2244: Home Office | J2244: United States | K2244: Pasadena | L2244: California | M2244: 91104 | N2244: West | O2244: OFF-ST-10003442 | P2244: Office Supplies | Q2244: Storage | R2244: Eldon Portable Mobile Manager | S2244: 56.56 | T2244: 2 | U2244: 0 | V2244: 15.2712
A2245: 2244 | B2245: CA-2014-103380 | C2245: =YEAR(Data!$D2245) -> 2014 | D2245: 41965 | E2245: 41969 | F2245: Standard Class | G2245: BF-11005 | H2245: Barry Franz | I2245: Home Office | J2245: United States | K2245: Pasadena | L2245: California | M2245: 91104 | N2245: West | O2245: OFF-AR-10003856 | P2245: Office Supplies | Q2245: Art | R2245: Newell 344 | S2245: 5.56 | T2245: 2 | U2245: 0 | V2245: 1.4456
A2246: 2245 | B2246: CA-2014-103380 | C2246: =YEAR(Data!$D2246) -> 2014 | D2246: 41965 | E2246: 41969 | F2246: Standard Class | G2246: BF-11005 | H2246: Barry Franz | I2246: Home Office | J2246: United States | K2246: Pasadena | L2246: California | M2246: 91104 | N2246: West | O2246: OFF-FA-10004248 | P2246: Office Supplies | Q2246: Fasteners | R2246: Advantus T-Pin Paper Clips | S2246: 9.02 | T2246: 2 | U2246: 0 | V2246: 3.5178
A2247: 2246 | B2247: CA-2014-103380 | C2247: =YEAR(Data!$D2247) -> 2014 | D2247: 41965 | E2247: 41969 | F2247: Standard Class | G2247: BF-11005 | H2247: Barry Franz | I2247: Home Office | J2247: United States | K2247: Pasadena | L2247: California | M2247: 91104 | N2247: West | O2247: OFF-AP-10001492 | P2247: Office Supplies | Q2247: Appliances | R2247: Acco Six-Outlet Power Strip, 4' Cord Length | S2247: 8.62 | T2247: 1 | U2247: 0 | V2247: 2.2412
A2248: 2247 | B2248: CA-2014-103380 | C2248: =YEAR(Data!$D2248) -> 2014 | D2248: 41965 | E2248: 41969 | F2248: Standard Class | G2248: BF-11005 | H2248: Barry Franz | I2248: Home Office | J2248: United States | K2248: Pasadena | L2248: California | M2248: 91104 | N2248: West | O2248: TEC-PH-10004165 | P2248: Technology | Q2248: Phones | R2248: Mitel MiVoice 5330e IP Phone | S2248: 659.976 | T2248: 3 | U2248: 0.2 | V2248: 49.4982
... A5275: 5274 | B5275: US-2013-158309 | C5275: =YEAR(Data!$D5275) -> 2013 | D5275: 41605 | E5275: 41608 | F5275: First Class | G5275: PA-19060 | H5275: Pete Armstrong | I5275: Home Office | J5275: United States | K5275: Miami | L5275: Florida | M5275: 33142 | N5275: South | O5275: OFF-BI-10000145 | P5275: Office Supplies | Q5275: Binders | R5275: Zipper Ring Binder Pockets | S5275: 3.744 | T5275: 4 | U5275: 0.7 | V5275: -2.6208
A5276: 5275 | B5276: CA-2012-162887 | C5276: =YEAR(Data!$D5276) -> 2012 | D5276: 41220 | E5276: 41222 | F5276: Second Class | G5276: SV-20785 | H5276: Stewart Visinsky | I5276: Consumer | J5276: United States | K5276: Burlington | L5276: Vermont | M5276: 05408 | N5276: East | O5276: FUR-CH-10000595 | P5276: Furniture | Q5276: Chairs | R5276: Safco Contoured Stacking Chairs | S5276: 715.2 | T5276: 3 | U5276: 0 | V5276: 178.8
A5277: 5276 | B5277: CA-2014-147333 | C5277: =YEAR(Data!$D5277) -> 2014 | D5277: 41988 | E5277: 41994 | F5277: Standard Class | G5277: KL-16555 | H5277: Kelly Lampkin | I5277: Corporate | J5277: United States | K5277: Fayetteville | L5277: Arkansas | M5277: 72701 | N5277: South | O5277: TEC-AC-10004469 | P5277: Technology | Q5277: Accessories | R5277: Microsoft Sculpt Comfort Mouse | S5277: 159.8 | T5277: 4 | U5277: 0 | V5277: 70.312
A5278: 5277 | B5278: CA-2014-147333 | C5278: =YEAR(Data!$D5278) -> 2014 | D5278: 41988 | E5278: 41994 | F5278: Standard Class | G5278: KL-16555 | H5278: Kelly Lampkin | I5278: Corporate | J5278: United States | K5278: Fayetteville | L5278: Arkansas | M5278: 72701 | N5278: South | O5278: TEC-AC-10003038 | P5278: Technology | Q5278: Accessories | R5278: Kingston Digital DataTraveler 16GB USB 2.0 | S5278: 44.75 | T5278: 5 | U5278: 0 | V5278: 8.5025
A5279: 5278 | B5279: CA-2011-113859 | C5279: =YEAR(Data!$D5279) -> 2011 | D5279: 40799 | E5279: 40803 | F5279: Standard Class | G5279: BC-11125 | H5279: Becky Castell | I5279: Home Office | J5279: United States | K5279: Odessa | L5279: Texas | M5279: 79762 | N5279: Central | O5279: FUR-CH-10004698 | P5279: Furniture | Q5279: Chairs | R5279: Padded Folding Chairs, Black, 4/Carton | S5279: 340.116 | T5279: 6 | U5279: 0.3 | V5279: -9.7176
A5280: 5279 | B5280: CA-2011-159681 | C5280: =YEAR(Data!$D5280) -> 2011 | D5280: 40884 | E5280: 40890 | F5280: Standard Class | G5280: PO-18850 | H5280: Patrick O'Brill | I5280: Consumer | J5280: United States | K5280: Virginia Beach | L5280: Virginia | M5280: 23464 | N5280: South | O5280: OFF-PA-10003641 | P5280: Office Supplies | Q5280: Paper | R5280: Xerox 1909 | S5280: 105.52 | T5280: 4 | U5280: 0 | V5280: 48.5392
A5281: 5280 | B5281: US-2014-104094 | C5281: =YEAR(Data!$D5281) -> 2014 | D5281: 41890 | E5281: 41894 | F5281: Standard Class | G5281: AG-10675 | H5281: Anna Gayman | I5281: Consumer | J5281: United States | K5281: Milwaukee | L5281: Wisconsin | M5281: 53209 | N5281: Central | O5281: TEC-AC-10002134 | P5281: Technology | Q5281: Accessories | R5281: Rosewill 107 Normal Keys USB Wired Standard Keyboard | S5281: 13.48 | T5281: 1 | U5281: 0 | V5281: 1.8872
A5282: 5281 | B5282: CA-2014-152709 | C5282: =YEAR(Data!$D5282) -> 2014 | D5282: 41920 | E5282: 41925 | F5282: Standard Class | G5282: DB-13210 | H5282: Dean Braden | I5282: Consumer | J5282: United States | K5282: Detroit | L5282: Michigan | M5282: 48234 | N5282: Central | O5282: OFF-ST-10001837 | P5282: Office Supplies | Q5282: Storage | R5282: SAFCO Mobile Desk Side File, Wire Frame | S5282: 85.52 | T5282: 2 | U5282: 0 | V5282: 22.2352
A5283: 5282 | B5283: CA-2012-105158 | C5283: =YEAR(Data!$D5283) -> 2012 | D5283: 41157 | E5283: 41162 | F5283: Standard Class | G5283: SP-20860 | H5283: Sung Pak | I5283: Corporate | J5283: United States | K5283: Rochester | L5283: Minnesota | M5283: 55901 | N5283: Central | O5283: FUR-FU-10001706 | P5283: Furniture | Q5283: Furnishings | R5283: Longer-Life Soft White Bulbs | S5283: 6.16 | T5283: 2 | U5283: 0 | V5283: 2.9568
A5284: 5283 | B5284: CA-2012-105158 | C5284: =YEAR(Data!$D5284) -> 2012 | D5284: 41157 | E5284: 41162 | F5284: Standard Class | G5284: SP-20860 | H5284: Sung Pak | I5284: Corporate | J5284: United States | K5284: Rochester | L5284: Minnesota | M5284: 55901 | N5284: Central | O5284: OFF-PA-10001970 | P5284: Office Supplies | Q5284: Paper | R5284: Xerox 1881 | S5284: 36.84 | T5284: 3 | U5284: 0 | V5284: 17.3148
A5285: 5284 | B5285: CA-2011-133424 | C5285: =YEAR(Data!$D5285) -> 2011 | D5285: 40632 | E5285: 40637 | F5285: Standard Class | G5285: Dl-13600 | H5285: Dorris liebe | I5285: Corporate | J5285: United States | K5285: Seattle | L5285: Washington | M5285: 98105 | N5285: West | O5285: OFF-ST-10002957 | P5285: Office Supplies | Q5285: Storage | R5285: Sterilite Show Offs Storage Containers | S5285: 15.84 | T5285: 3 | U5285: 0 | V5285: 0
A5286: 5285 | B5286: CA-2011-133424 | C5286: =YEAR(Data!$D5286) -> 2011 | D5286: 40632 | E5286: 40637 | F5286: Standard Class | G5286: Dl-13600 | H5286: Dorris liebe | I5286: Corporate | J5286: United States | K5286: Seattle | L5286: Washington | M5286: 98105 | N5286: West | O5286: OFF-LA-10002312 | P5286: Office Supplies | Q5286: Labels | R5286: Avery 490 | S5286: 44.4 | T5286: 3 | U5286: 0 | V5286: 22.2
A5287: 5286 | B5287: CA-2014-105991 | C5287: =YEAR(Data!$D5287) -> 2014 | D5287: 41765 | E5287: 41766 | F5287: First Class | G5287: LH-17020 | H5287: Lisa Hazard | I5287: Consumer | J5287: United States | K5287: Louisville | L5287: Colorado | M5287: 80027 | N5287: West | O5287: OFF-EN-10002600 | P5287: Office Supplies | Q5287: Envelopes | R5287: Redi-Strip #10 Envelopes, 4 1/8 x 9 1/2 | S5287: 21.24 | T5287: 9 | U5287: 0.2 | V5287: 7.434
A5288: 5287 | B5288: CA-2014-105991 | C5288: =YEAR(Data!$D5288) -> 2014 | D5288: 41765 | E5288: 41766 | F5288: First Class | G5288: LH-17020 | H5288: Lisa Hazard | I5288: Consumer | J5288: United States | K5288: Louisville | L5288: Colorado | M5288: 80027 | N5288: West | O5288: OFF-BI-10003274 | P5288: Office Supplies | Q5288: Binders | R5288: Avery Durable Slant Ring Binders, No Labels | S5288: 9.552 | T5288: 8 | U5288: 0.7 | V5288: -7.3232
... A8799: 8798 | B8799: CA-2013-106397 | C8799: =YEAR(Data!$D8799) -> 2013 | D8799: 41463 | E8799: 41469 | F8799: Standard Class | G8799: MJ-17740 | H8799: Max Jones | I8799: Consumer | J8799: United States | K8799: Orem | L8799: Utah | M8799: 84057 | N8799: West | O8799: OFF-AR-10004602 | P8799: Office Supplies | Q8799: Art | R8799: Boston KS Multi-Size Manual Pencil Sharpener | S8799: 45.98 | T8799: 2 | U8799: 0 | V8799: 12.8744
A8800: 8799 | B8800: US-2013-150140 | C8800: =YEAR(Data!$D8800) -> 2013 | D8800: 41371 | E8800: 41375 | F8800: Standard Class | G8800: VM-21685 | H8800: Valerie Mitchum | I8800: Home Office | J8800: United States | K8800: Burlington | L8800: Vermont | M8800: 05408 | N8800: East | O8800: TEC-PH-10002555 | P8800: Technology | Q8800: Phones | R8800: Nortel Meridian M5316 Digital phone | S8800: 1294.75 | T8800: 5 | U8800: 0 | V8800: 336.635
A8801: 8800 | B8801: CA-2011-116666 | C8801: =YEAR(Data!$D8801) -> 2011 | D8801: 40671 | E8801: 40673 | F8801: First Class | G8801: KT-16480 | H8801: Kean Thornton | I8801: Consumer | J8801: United States | K8801: Philadelphia | L8801: Pennsylvania | M8801: 19134 | N8801: East | O8801: TEC-CO-10001449 | P8801: Technology | Q8801: Copiers | R8801: Hewlett Packard LaserJet 3310 Copier | S8801: 1799.97 | T8801: 5 | U8801: 0.4 | V8801: 239.996
A8802: 8801 | B8802: CA-2014-148992 | C8802: =YEAR(Data!$D8802) -> 2014 | D8802: 41967 | E8802: 41971 | F8802: Standard Class | G8802: CS-12250 | H8802: Chris Selesnick | I8802: Corporate | J8802: United States | K8802: Chicago | L8802: Illinois | M8802: 60623 | N8802: Central | O8802: OFF-PA-10004285 | P8802: Office Supplies | Q8802: Paper | R8802: Xerox 1959 | S8802: 10.688 | T8802: 2 | U8802: 0.2 | V8802: 3.7408
A8803: 8802 | B8803: CA-2013-140935 | C8803: =YEAR(Data!$D8803) -> 2013 | D8803: 41589 | E8803: 41591 | F8803: First Class | G8803: AB-10015 | H8803: Aaron Bergman | I8803: Consumer | J8803: United States | K8803: Oklahoma City | L8803: Oklahoma | M8803: 73120 | N8803: Central | O8803: TEC-PH-10000562 | P8803: Technology | Q8803: Phones | R8803: Samsung Convoy 3 | S8803: 221.98 | T8803: 2 | U8803: 0 | V8803: 62.1544
A8804: 8803 | B8804: CA-2013-140935 | C8804: =YEAR(Data!$D8804) -> 2013 | D8804: 41589 | E8804: 41591 | F8804: First Class | G8804: AB-10015 | H8804: Aaron Bergman | I8804: Consumer | J8804: United States | K8804: Oklahoma City | L8804: Oklahoma | M8804: 73120 | N8804: Central | O8804: FUR-BO-10003966 | P8804: Furniture | Q8804: Bookcases | R8804: Sauder Facets Collection Library, Sky Alder Finish | S8804: 341.96 | T8804: 2 | U8804: 0 | V8804: 54.7136
A8805: 8804 | B8805: CA-2011-157644 | C8805: =YEAR(Data!$D8805) -> 2011 | D8805: 40908 | E8805: 40909 | F8805: First Class | G8805: AH-10030 | H8805: Aaron Hawkins | I8805: Corporate | J8805: United States | K8805: New York City | L8805: New York | M8805: 10035 | N8805: East | O8805: TEC-AC-10003614 | P8805: Technology | Q8805: Accessories | R8805: Verbatim 25 GB 6x Blu-ray Single Layer Recordable Disc, 10/Pack | S8805: 34.77 | T8805: 3 | U8805: 0 | V8805: 11.4741
A8806: 8805 | B8806: CA-2011-157644 | C8806: =YEAR(Data!$D8806) -> 2011 | D8806: 40908 | E8806: 40909 | F8806: First Class | G8806: AH-10030 | H8806: Aaron Hawkins | I8806: Corporate | J8806: United States | K8806: New York City | L8806: New York | M8806: 10035 | N8806: East | O8806: OFF-LA-10003148 | P8806: Office Supplies | Q8806: Labels | R8806: Avery 51 | S8806: 18.9 | T8806: 3 | U8806: 0 | V8806: 8.694
A8807: 8806 | B8807: US-2014-100398 | C8807: =YEAR(Data!$D8807) -> 2014 | D8807: 41871 | E8807: 41875 | F8807: Standard Class | G8807: DO-13435 | H8807: Denny Ordway | I8807: Consumer | J8807: United States | K8807: Salt Lake City | L8807: Utah | M8807: 84106 | N8807: West | O8807: OFF-BI-10002133 | P8807: Office Supplies | Q8807: Binders | R8807: Wilson Jones Elliptical Ring 3 1/2" Capacity Binders, 800 sheets | S8807: 102.72 | T8807: 3 | U8807: 0.2 | V8807: 37.236
A8808: 8807 | B8808: CA-2013-113082 | C8808: =YEAR(Data!$D8808) -> 2013 | D8808: 41530 | E8808: 41534 | F8808: Standard Class | G8808: MC-17590 | H8808: Matt Collister | I8808: Corporate | J8808: United States | K8808: Utica | L8808: New York | M8808: 13501 | N8808: East | O8808: FUR-FU-10002813 | P8808: Furniture | Q8808: Furnishings | R8808: DAX Contemporary Wood Frame with Silver Metal Mat, Desktop, 11 x 14 Size | S8808: 40.48 | T8808: 2 | U8808: 0 | V8808: 14.5728
A8809: 8808 | B8809: US-2014-110646 | C8809: =YEAR(Data!$D8809) -> 2014 | D8809: 41939 | E8809: 41944 | F8809: Standard Class | G8809: JF-15190 | H8809: Jamie Frazer | I8809: Consumer | J8809: United States | K8809: Philadelphia | L8809: Pennsylvania | M8809: 19134 | N8809: East | O8809: OFF-BI-10004330 | P8809: Office Supplies | Q8809: Binders | R8809: GBC Velobind Prepunched Cover Sets, Regency Series | S8809: 33.282 | T8809: 3 | U8809: 0.7 | V8809: -27.735
A8810: 8809 | B8810: US-2014-110646 | C8810: =YEAR(Data!$D8810) -> 2014 | D8810: 41939 | E8810: 41944 | F8810: Standard Class | G8810: JF-15190 | H8810: Jamie Frazer | I8810: Consumer | J8810: United States | K8810: Philadelphia | L8810: Pennsylvania | M8810: 19134 | N8810: East | O8810: TEC-PH-10002807 | P8810: Technology | Q8810: Phones | R8810: Motorla HX550 Universal Bluetooth Headset | S8810: 118.65 | T8810: 5 | U8810: 0.4 | V8810: 19.775
A8811: 8810 | B8811: US-2014-110646 | C8811: =YEAR(Data!$D8811) -> 2014 | D8811: 41939 | E8811: 41944 | F8811: Standard Class | G8811: JF-15190 | H8811: Jamie Frazer | I8811: Consumer | J8811: United States | K8811: Philadelphia | L8811: Pennsylvania | M8811: 19134 | N8811: East | O8811: OFF-LA-10001404 | P8811: Office Supplies | Q8811: Labels | R8811: Avery 517 | S8811: 14.76 | T8811: 5 | U8811: 0.2 | V8811: 4.9815
A8812: 8811 | B8812: CA-2014-120614 | C8812: =YEAR(Data!$D8812) -> 2014 | D8812: 41790 | E8812: 41795 | F8812: Standard Class | G8812: SM-20950 | H8812: Suzanne McNair | I8812: Corporate | J8812: United States | K8812: Los Angeles | L8812: California | M8812: 90004 | N8812: West | O8812: OFF-PA-10004911 | P8812: Office Supplies | Q8812: Paper | R8812: Rediform S.O.S. 1-Up Phone Message Bk, 4-1/4x3-1/16 Bk, 1 Form/Pg, 40 Messages/Bk, 3/Pk | S8812: 37.52 | T8812: 4 | U8812: 0 | V8812: 18.0096
... A9147: 9146 | B9147: CA-2012-126970 | C9147: =YEAR(Data!$D9147) -> 2012 | D9147: 41172 | E9147: 41176 | F9147: Standard Class | G9147: TP-21130 | H9147: Theone Pippenger | I9147: Consumer | J9147: United States | K9147: Naperville | L9147: Illinois | M9147: 60540 | N9147: Central | O9147: OFF-BI-10000138 | P9147: Office Supplies | Q9147: Binders | R9147: Acco Translucent Poly Ring Binders | S9147: 2.808 | T9147: 3 | U9147: 0.8 | V9147: -4.4928
A9148: 9147 | B9148: US-2013-165505 | C9148: =YEAR(Data!$D9148) -> 2013 | D9148: 41297 | E9148: 41301 | F9148: Standard Class | G9148: CB-12535 | H9148: Claudia Bergmann | I9148: Corporate | J9148: United States | K9148: Burlington | L9148: Vermont | M9148: 05408 | N9148: East | O9148: TEC-AC-10002926 | P9148: Technology | Q9148: Accessories | R9148: Logitech Wireless Marathon Mouse M705 | S9148: 99.98 | T9148: 2 | U9148: 0 | V9148: 42.9914
A9149: 9148 | B9149: US-2013-165505 | C9149: =YEAR(Data!$D9149) -> 2013 | D9149: 41297 | E9149: 41301 | F9149: Standard Class | G9149: CB-12535 | H9149: Claudia Bergmann | I9149: Corporate | J9149: United States | K9149: Burlington | L9149: Vermont | M9149: 05408 | N9149: East | O9149: OFF-AR-10003477 | P9149: Office Supplies | Q9149: Art | R9149: 4009 Highlighters | S9149: 8.04 | T9149: 6 | U9149: 0 | V9149: 2.7336
A9150: 9149 | B9150: US-2013-165505 | C9150: =YEAR(Data!$D9150) -> 2013 | D9150: 41297 | E9150: 41301 | F9150: Standard Class | G9150: CB-12535 | H9150: Claudia Bergmann | I9150: Corporate | J9150: United States | K9150: Burlington | L9150: Vermont | M9150: 05408 | N9150: East | O9150: OFF-ST-10001526 | P9150: Office Supplies | Q9150: Storage | R9150: Iceberg Mobile Mega Data/Printer Cart | S9150: 1564.29 | T9150: 13 | U9150: 0 | V9150: 406.7154
A9151: 9150 | B9151: US-2011-157070 | C9151: =YEAR(Data!$D9151) -> 2011 | D9151: 40695 | E9151: 40700 | F9151: Standard Class | G9151: QJ-19255 | H9151: Quincy Jones | I9151: Corporate | J9151: United States | K9151: Detroit | L9151: Michigan | M9151: 48234 | N9151: Central | O9151: OFF-BI-10001765 | P9151: Office Supplies | Q9151: Binders | R9151: Wilson Jones Heavy-Duty Casebound Ring Binders with Metal Hinges | S9151: 138.56 | T9151: 4 | U9151: 0 | V9151: 66.5088
A9152: 9151 | B9152: US-2011-157070 | C9152: =YEAR(Data!$D9152) -> 2011 | D9152: 40695 | E9152: 40700 | F9152: Standard Class | G9152: QJ-19255 | H9152: Quincy Jones | I9152: Corporate | J9152: United States | K9152: Detroit | L9152: Michigan | M9152: 48234 | N9152: Central | O9152: OFF-AP-10004859 | P9152: Office Supplies | Q9152: Appliances | R9152: Acco 6 Outlet Guardian Premium Surge Suppressor | S9152: 65.52 | T9152: 5 | U9152: 0.1 | V9152: 12.376
A9153: 9152 | B9153: US-2012-106873 | C9153: =YEAR(Data!$D9153) -> 2012 | D9153: 41176 | E9153: 41181 | F9153: Second Class | G9153: KM-16720 | H9153: Kunst Miller | I9153: Consumer | J9153: United States | K9153: Avondale | L9153: Arizona | M9153: 85323 | N9153: West | O9153: OFF-AR-10003179 | P9153: Office Supplies | Q9153: Art | R9153: Dixon Ticonderoga Core-Lock Colored Pencils | S9153: 14.576 | T9153: 2 | U9153: 0.2 | V9153: 2.3686
A9154: 9153 | B9154: US-2012-106873 | C9154: =YEAR(Data!$D9154) -> 2012 | D9154: 41176 | E9154: 41181 | F9154: Second Class | G9154: KM-16720 | H9154: Kunst Miller | I9154: Consumer | J9154: United States | K9154: Avondale | L9154: Arizona | M9154: 85323 | N9154: West | O9154: TEC-AC-10002345 | P9154: Technology | Q9154: Accessories | R9154: HP Standard 104 key PS/2 Keyboard | S9154: 23.2 | T9154: 2 | U9154: 0.2 | V9154: 1.45
A9155: 9154 | B9155: US-2012-106873 | C9155: =YEAR(Data!$D9155) -> 2012 | D9155: 41176 | E9155: 41181 | F9155: Second Class | G9155: KM-16720 | H9155: Kunst Miller | I9155: Consumer | J9155: United States | K9155: Avondale | L9155: Arizona | M9155: 85323 | N9155: West | O9155: OFF-AR-10001246 | P9155: Office Supplies | Q9155: Art | R9155: Newell 317 | S9155: 16.464 | T9155: 7 | U9155: 0.2 | V9155: 1.8522
A9156: 9155 | B9156: CA-2013-132990 | C9156: =YEAR(Data!$D9156) -> 2013 | D9156: 41488 | E9156: 41490 | F9156: Second Class | G9156: KM-16660 | H9156: Khloe Miller | I9156: Consumer | J9156: United States | K9156: Philadelphia | L9156: Pennsylvania | M9156: 19140 | N9156: East | O9156: FUR-FU-10004864 | P9156: Furniture | Q9156: Furnishings | R9156: Eldon 500 Class Desk Accessories | S9156: 19.312 | T9156: 2 | U9156: 0.2 | V9156: 3.1382
A9157: 9156 | B9157: CA-2011-102645 | C9157: =YEAR(Data!$D9157) -> 2011 | D9157: 40567 | E9157: 40572 | F9157: Standard Class | G9157: IM-15055 | H9157: Ionia McGrath | I9157: Consumer | J9157: United States | K9157: Las Vegas | L9157: Nevada | M9157: 89115 | N9157: West | O9157: OFF-PA-10001804 | P9157: Office Supplies | Q9157: Paper | R9157: Xerox 195 | S9157: 40.08 | T9157: 6 | U9157: 0 | V9157: 19.2384
A9158: 9157 | B9158: CA-2011-134215 | C9158: =YEAR(Data!$D9158) -> 2011 | D9158: 40759 | E9158: 40763 | F9158: Standard Class | G9158: ML-17395 | H9158: Marina Lichtenstein | I9158: Corporate | J9158: United States | K9158: Bangor | L9158: Maine | M9158: 4401 | N9158: East | O9158: OFF-AP-10001271 | P9158: Office Supplies | Q9158: Appliances | R9158: Eureka The Boss Cordless Rechargeable Stick Vac | S9158: 101.96 | T9158: 2 | U9158: 0 | V9158: 27.5292
A9159: 9158 | B9159: CA-2011-134215 | C9159: =YEAR(Data!$D9159) -> 2011 | D9159: 40759 | E9159: 40763 | F9159: Standard Class | G9159: ML-17395 | H9159: Marina Lichtenstein | I9159: Corporate | J9159: United States | K9159: Bangor | L9159: Maine | M9159: 4401 | N9159: East | O9159: OFF-PA-10004353 | P9159: Office Supplies | Q9159: Paper | R9159: Southworth 25% Cotton Premium Laser Paper and Envelopes | S9159: 259.74 | T9159: 13 | U9159: 0 | V9159: 124.6752
A9160: 9159 | B9160: CA-2011-134215 | C9160: =YEAR(Data!$D9160) -> 2011 | D9160: 40759 | E9160: 40763 | F9160: Standard Class | G9160: ML-17395 | H9160: Marina Lichtenstein | I9160: Corporate | J9160: United States | K9160: Bangor | L9160: Maine | M9160: 4401 | N9160: East | O9160: TEC-AC-10002473 | P9160: Technology | Q9160: Accessories | R9160: Maxell 4.7GB DVD-R | S9160: 255.42 | T9160: 9 | U9160: 0 | V9160: 104.7222
A9161: 9160 | B9161: CA-2013-118934 | C9161: =YEAR(Data!$D9161) -> 2013 | D9161: 41496 | E9161: 41501 | F9161: Standard Class | G9161: GH-14410 | H9161: Gary Hansen | I9161: Home Office | J9161: United States | K9161: Hendersonville | L9161: Tennessee | M9161: 37075 | N9161: South | O9161: OFF-BI-10003314 | P9161: Office Supplies | Q9161: Binders | R9161: Tuff Stuff Recycled Round Ring Binders | S9161: 4.338 | T9161: 3 | U9161: 0.7 | V9161: -3.0366
A9162: 9161 | B9162: CA-2013-118934 | C9162: =YEAR(Data!$D9162) -> 2013 | D9162: 41496 | E9162: 41501 | F9162: Standard Class | G9162: GH-14410 | H9162: Gary Hansen | I9162: Home Office | J9162: United States | K9162: Hendersonville | L9162: Tennessee | M9162: 37075 | N9162: South | O9162: OFF-BI-10004465 | P9162: Office Supplies | Q9162: Binders | R9162: Avery Durable Slant Ring Binders | S9162: 11.88 | T9162: 5 | U9162: 0.7 | V9162: -7.92
... A9387: 9386 | B9387: CA-2014-163097 | C9387: =YEAR(Data!$D9387) -> 2014 | D9387: 41879 | E9387: 41883 | F9387: Standard Class | G9387: SF-20200 | H9387: Sarah Foster | I9387: Consumer | J9387: United States | K9387: Mesa | L9387: Arizona | M9387: 85204 | N9387: West | O9387: FUR-FU-10004973 | P9387: Furniture | Q9387: Furnishings | R9387: Flat Face Poster Frame | S9387: 120.576 | T9387: 8 | U9387: 0.2 | V9387: 33.1584
A9388: 9387 | B9388: US-2014-127292 | C9388: =YEAR(Data!$D9388) -> 2014 | D9388: 41659 | E9388: 41663 | F9388: Standard Class | G9388: RM-19375 | H9388: Raymond Messe | I9388: Consumer | J9388: United States | K9388: Burlington | L9388: Vermont | M9388: 05408 | N9388: East | O9388: OFF-PA-10000157 | P9388: Office Supplies | Q9388: Paper | R9388: Xerox 191 | S9388: 79.92 | T9388: 4 | U9388: 0 | V9388: 37.5624
A9389: 9388 | B9389: US-2014-127292 | C9389: =YEAR(Data!$D9389) -> 2014 | D9389: 41659 | E9389: 41663 | F9389: Standard Class | G9389: RM-19375 | H9389: Raymond Messe | I9389: Consumer | J9389: United States | K9389: Burlington | L9389: Vermont | M9389: 05408 | N9389: East | O9389: OFF-PA-10001970 | P9389: Office Supplies | Q9389: Paper | R9389: Xerox 1881 | S9389: 12.28 | T9389: 1 | U9389: 0 | V9389: 5.7716
A9390: 9389 | B9390: US-2014-127292 | C9390: =YEAR(Data!$D9390) -> 2014 | D9390: 41659 | E9390: 41663 | F9390: Standard Class | G9390: RM-19375 | H9390: Raymond Messe | I9390: Consumer | J9390: United States | K9390: Burlington | L9390: Vermont | M9390: 05408 | N9390: East | O9390: OFF-AP-10000828 | P9390: Office Supplies | Q9390: Appliances | R9390: Avanti 4.4 Cu. Ft. Refrigerator | S9390: 542.94 | T9390: 3 | U9390: 0 | V9390: 152.0232
A9391: 9390 | B9391: US-2014-127292 | C9391: =YEAR(Data!$D9391) -> 2014 | D9391: 41659 | E9391: 41663 | F9391: Standard Class | G9391: RM-19375 | H9391: Raymond Messe | I9391: Consumer | J9391: United States | K9391: Burlington | L9391: Vermont | M9391: 05408 | N9391: East | O9391: OFF-EN-10001509 | P9391: Office Supplies | Q9391: Envelopes | R9391: Poly String Tie Envelopes | S9391: 2.04 | T9391: 1 | U9391: 0 | V9391: 0.9588
A9392: 9391 | B9392: CA-2012-163734 | C9392: =YEAR(Data!$D9392) -> 2012 | D9392: 41079 | E9392: 41084 | F9392: Standard Class | G9392: KM-16375 | H9392: Katherine Murray | I9392: Home Office | J9392: United States | K9392: Houston | L9392: Texas | M9392: 77070 | N9392: Central | O9392: OFF-ST-10003692 | P9392: Office Supplies | Q9392: Storage | R9392: Recycled Steel Personal File for Hanging File Folders | S9392: 228.92 | T9392: 5 | U9392: 0.2 | V9392: 14.3075
A9393: 9392 | B9393: CA-2014-162474 | C9393: =YEAR(Data!$D9393) -> 2014 | D9393: 41712 | E9393: 41715 | F9393: First Class | G9393: FH-14275 | H9393: Frank Hawley | I9393: Corporate | J9393: United States | K9393: Aurora | L9393: Illinois | M9393: 60505 | N9393: Central | O9393: TEC-PH-10004700 | P9393: Technology | Q9393: Phones | R9393: PowerGen Dual USB Car Charger | S9393: 7.992 | T9393: 1 | U9393: 0.2 | V9393: 2.5974
A9394: 9393 | B9394: CA-2012-130848 | C9394: =YEAR(Data!$D9394) -> 2012 | D9394: 41207 | E9394: 41207 | F9394: Same Day | G9394: DG-13300 | H9394: Deirdre Greer | I9394: Corporate | J9394: United States | K9394: Denver | L9394: Colorado | M9394: 80219 | N9394: West | O9394: FUR-CH-10000422 | P9394: Furniture | Q9394: Chairs | R9394: Global Highback Leather Tilter in Burgundy | S9394: 582.336 | T9394: 8 | U9394: 0.2 | V9394: -29.1168
A9395: 9394 | B9395: CA-2011-125997 | C9395: =YEAR(Data!$D9395) -> 2011 | D9395: 40806 | E9395: 40809 | F9395: First Class | G9395: MW-18220 | H9395: Mitch Webber | I9395: Consumer | J9395: United States | K9395: New York City | L9395: New York | M9395: 10011 | N9395: East | O9395: TEC-PH-10003484 | P9395: Technology | Q9395: Phones | R9395: Ooma Telo VoIP Home Phone System | S9395: 629.95 | T9395: 5 | U9395: 0 | V9395: 157.4875
A9396: 9395 | B9396: CA-2011-125997 | C9396: =YEAR(Data!$D9396) -> 2011 | D9396: 40806 | E9396: 40809 | F9396: First Class | G9396: MW-18220 | H9396: Mitch Webber | I9396: Consumer | J9396: United States | K9396: New York City | L9396: New York | M9396: 10011 | N9396: East | O9396: FUR-CH-10001394 | P9396: Furniture | Q9396: Chairs | R9396: Global Leather Executive Chair | S9396: 631.782 | T9396: 2 | U9396: 0.1 | V9396: 140.396
A9397: 9396 | B9397: CA-2011-125997 | C9397: =YEAR(Data!$D9397) -> 2011 | D9397: 40806 | E9397: 40809 | F9397: First Class | G9397: MW-18220 | H9397: Mitch Webber | I9397: Consumer | J9397: United States | K9397: New York City | L9397: New York | M9397: 10011 | N9397: East | O9397: FUR-BO-10002213 | P9397: Furniture | Q9397: Bookcases | R9397: DMI Eclipse Executive Suite Bookcases | S9397: 801.568 | T9397: 2 | U9397: 0.2 | V9397: -10.0196
A9398: 9397 | B9398: CA-2011-125997 | C9398: =YEAR(Data!$D9398) -> 2011 | D9398: 40806 | E9398: 40809 | F9398: First Class | G9398: MW-18220 | H9398: Mitch Webber | I9398: Consumer | J9398: United States | K9398: New York City | L9398: New York | M9398: 10011 | N9398: East | O9398: OFF-LA-10002762 | P9398: Office Supplies | Q9398: Labels | R9398: Avery 485 | S9398: 75.18 | T9398: 6 | U9398: 0 | V9398: 35.3346
A9399: 9398 | B9399: CA-2011-125997 | C9399: =YEAR(Data!$D9399) -> 2011 | D9399: 40806 | E9399: 40809 | F9399: First Class | G9399: MW-18220 | H9399: Mitch Webber | I9399: Consumer | J9399: United States | K9399: New York City | L9399: New York | M9399: 10011 | N9399: East | O9399: OFF-AP-10003842 | P9399: Office Supplies | Q9399: Appliances | R9399: Euro-Pro Shark Turbo Vacuum | S9399: 30.98 | T9399: 1 | U9399: 0 | V9399: 8.0548
A9400: 9399 | B9400: CA-2011-125997 | C9400: =YEAR(Data!$D9400) -> 2011 | D9400: 40806 | E9400: 40809 | F9400: First Class | G9400: MW-18220 | H9400: Mitch Webber | I9400: Consumer | J9400: United States | K9400: New York City | L9400: New York | M9400: 10011 | N9400: East | O9400: TEC-PH-10003072 | P9400: Technology | Q9400: Phones | R9400: Panasonic KX-TG9541B DECT 6.0 Digital 2-Line Expandable Cordless Phone With Digital Answering System | S9400: 1349.91 | T9400: 9 | U9400: 0 | V9400: 661.4559
A9401: 9400 | B9401: CA-2013-103128 | C9401: =YEAR(Data!$D9401) -> 2013 | D9401: 41590 | E9401: 41594 | F9401: Standard Class | G9401: SC-20845 | H9401: Sung Chung | I9401: Consumer | J9401: United States | K9401: Arlington Heights | L9401: Illinois | M9401: 60004 | N9401: Central | O9401: OFF-AR-10003394 | P9401: Office Supplies | Q9401: Art | R9401: Newell 332 | S9401: 14.112 | T9401: 6 | U9401: 0.2 | V9401: 1.2348
A9402: 9401 | B9402: CA-2012-167696 | C9402: =YEAR(Data!$D9402) -> 2012 | D9402: 41168 | E9402: 41173 | F9402: Standard Class | G9402: BD-11500 | H9402: Bradley Drucker | I9402: Consumer | J9402: United States | K9402: Newport News | L9402: Virginia | M9402: 23602 | N9402: South | O9402: OFF-EN-10001539 | P9402: Office Supplies | Q9402: Envelopes | R9402: Staples | S9402: 31.12 | T9402: 4 | U9402: 0 | V9402: 14.6264
A9403: 9402 | B9403: CA-2011-159814 | C9403: =YEAR(Data!$D9403) -> 2011 | D9403: 40718 | E9403: 40722 | F9403: Standard Class | G9403: LP-17080 | H9403: Liz Pelletier | I9403: Consumer | J9403: United States | K9403: Tucson | L9403: Arizona | M9403: 85705 | N9403: West | O9403: FUR-FU-10001731 | P9403: Furniture | Q9403: Furnishings | R9403: Acrylic Self-Standing Desk Frames | S9403: 4.272 | T9403: 2 | U9403: 0.2 | V9403: 0.9612
... A9742: 9741 | B9742: CA-2014-129294 | C9742: =YEAR(Data!$D9742) -> 2014 | D9742: 41715 | E9742: 41720 | F9742: Standard Class | G9742: KD-16615 | H9742: Ken Dana | I9742: Corporate | J9742: United States | K9742: Los Angeles | L9742: California | M9742: 90032 | N9742: West | O9742: OFF-AP-10001154 | P9742: Office Supplies | Q9742: Appliances | R9742: Bionaire Personal Warm Mist Humidifier/Vaporizer | S9742: 140.67 | T9742: 3 | U9742: 0 | V9742: 54.8613
A9743: 9742 | B9743: CA-2012-117086 | C9743: =YEAR(Data!$D9743) -> 2012 | D9743: 41221 | E9743: 41225 | F9743: Standard Class | G9743: QJ-19255 | H9743: Quincy Jones | I9743: Corporate | J9743: United States | K9743: Burlington | L9743: Vermont | M9743: 05408 | N9743: East | O9743: FUR-BO-10004834 | P9743: Furniture | Q9743: Bookcases | R9743: Riverside Palais Royal Lawyers Bookcase, Royale Cherry Finish | S9743: 4404.9 | T9743: 5 | U9743: 0 | V9743: 1013.127
A9744: 9743 | B9744: CA-2014-131303 | C9744: =YEAR(Data!$D9744) -> 2014 | D9744: 41972 | E9744: 41976 | F9744: Standard Class | G9744: EP-13915 | H9744: Emily Phan | I9744: Consumer | J9744: United States | K9744: San Diego | L9744: California | M9744: 92037 | N9744: West | O9744: OFF-LA-10001074 | P9744: Office Supplies | Q9744: Labels | R9744: Round Specialty Laser Printer Labels | S9744: 62.65 | T9744: 5 | U9744: 0 | V9744: 29.4455
A9745: 9744 | B9745: CA-2013-137127 | C9745: =YEAR(Data!$D9745) -> 2013 | D9745: 41442 | E9745: 41448 | F9745: Standard Class | G9745: JJ-15445 | H9745: Jennifer Jackson | I9745: Consumer | J9745: United States | K9745: Newark | L9745: Delaware | M9745: 19711 | N9745: East | O9745: OFF-LA-10001641 | P9745: Office Supplies | Q9745: Labels | R9745: Avery 518 | S9745: 9.45 | T9745: 3 | U9745: 0 | V9745: 4.536
A9746: 9745 | B9746: CA-2014-141782 | C9746: =YEAR(Data!$D9746) -> 2014 | D9746: 41661 | E9746: 41665 | F9746: Standard Class | G9746: BE-11410 | H9746: Bobby Elias | I9746: Consumer | J9746: United States | K9746: Aurora | L9746: Illinois | M9746: 60505 | N9746: Central | O9746: OFF-EN-10002230 | P9746: Office Supplies | Q9746: Envelopes | R9746: Airmail Envelopes | S9746: 268.576 | T9746: 4 | U9746: 0.2 | V9746: 90.6444
A9747: 9746 | B9747: CA-2014-137505 | C9747: =YEAR(Data!$D9747) -> 2014 | D9747: 41968 | E9747: 41968 | F9747: Same Day | G9747: BP-11290 | H9747: Beth Paige | I9747: Consumer | J9747: United States | K9747: Los Angeles | L9747: California | M9747: 90008 | N9747: West | O9747: FUR-TA-10000617 | P9747: Furniture | Q9747: Tables | R9747: Hon Practical Foundations 30 x 60 Training Table, Light Gray/Charcoal | S9747: 364.08 | T9747: 2 | U9747: 0.2 | V9747: 9.102
A9748: 9747 | B9748: CA-2014-137505 | C9748: =YEAR(Data!$D9748) -> 2014 | D9748: 41968 | E9748: 41968 | F9748: Same Day | G9748: BP-11290 | H9748: Beth Paige | I9748: Consumer | J9748: United States | K9748: Los Angeles | L9748: California | M9748: 90008 | N9748: West | O9748: FUR-TA-10001676 | P9748: Furniture | Q9748: Tables | R9748: Hon 61000 Series Interactive Training Tables | S9748: 71.088 | T9748: 2 | U9748: 0.2 | V9748: -1.7772
A9749: 9748 | B9749: US-2011-140914 | C9749: =YEAR(Data!$D9749) -> 2011 | D9749: 40858 | E9749: 40862 | F9749: Standard Class | G9749: BH-11710 | H9749: Brosina Hoffman | I9749: Consumer | J9749: United States | K9749: Chicago | L9749: Illinois | M9749: 60653 | N9749: Central | O9749: FUR-FU-10000175 | P9749: Furniture | Q9749: Furnishings | R9749: DAX Wood Document Frame. | S9749: 10.984 | T9749: 2 | U9749: 0.6 | V9749: -7.9634
A9750: 9749 | B9750: US-2011-140914 | C9750: =YEAR(Data!$D9750) -> 2011 | D9750: 40858 | E9750: 40862 | F9750: Standard Class | G9750: BH-11710 | H9750: Brosina Hoffman | I9750: Consumer | J9750: United States | K9750: Chicago | L9750: Illinois | M9750: 60653 | N9750: Central | O9750: FUR-CH-10003379 | P9750: Furniture | Q9750: Chairs | R9750: Global Commerce Series High-Back Swivel/Tilt Chairs | S9750: 797.944 | T9750: 4 | U9750: 0.3 | V9750: -56.996
A9751: 9750 | B9751: CA-2013-158358 | C9751: =YEAR(Data!$D9751) -> 2013 | D9751: 41338 | E9751: 41342 | F9751: Standard Class | G9751: EM-13810 | H9751: Eleni McCrary | I9751: Corporate | J9751: United States | K9751: Dover | L9751: New Hampshire | M9751: 3820 | N9751: East | O9751: TEC-AC-10002567 | P9751: Technology | Q9751: Accessories | R9751: Logitech G602 Wireless Gaming Mouse | S9751: 159.98 | T9751: 2 | U9751: 0 | V9751: 57.5928
A9752: 9751 | B9752: CA-2013-113390 | C9752: =YEAR(Data!$D9752) -> 2013 | D9752: 41559 | E9752: 41563 | F9752: Standard Class | G9752: EP-13915 | H9752: Emily Phan | I9752: Consumer | J9752: United States | K9752: Chicago | L9752: Illinois | M9752: 60610 | N9752: Central | O9752: OFF-AR-10003183 | P9752: Office Supplies | Q9752: Art | R9752: Avery Fluorescent Highlighter Four-Color Set | S9752: 5.344 | T9752: 2 | U9752: 0.2 | V9752: 0.668
A9753: 9752 | B9753: CA-2013-113390 | C9753: =YEAR(Data!$D9753) -> 2013 | D9753: 41559 | E9753: 41563 | F9753: Standard Class | G9753: EP-13915 | H9753: Emily Phan | I9753: Consumer | J9753: United States | K9753: Chicago | L9753: Illinois | M9753: 60610 | N9753: Central | O9753: OFF-AR-10001446 | P9753: Office Supplies | Q9753: Art | R9753: Newell 309 | S9753: 27.72 | T9753: 3 | U9753: 0.2 | V9753: 3.465
...

Sheet layout
A11: `` | B11: =#REF! -> #REF!

Sheet Dashboard1
